CHANGELOG.txt
LICENCE.txt
MANIFEST.in
README.txt
setup.py
vdevapi/__init__.py
vdevapi.egg-info/PKG-INFO
vdevapi.egg-info/SOURCES.txt
vdevapi.egg-info/dependency_links.txt
vdevapi.egg-info/requires.txt
vdevapi.egg-info/top_level.txt