Metadata-Version: 1.1
Name: vdevapi
Version: 0.0.2
Summary: An API, that can do a lots of cool things.
Home-page: UNKNOWN
Author: Michael Ďalog
Author-email: michaelvertexxdalog@gmail.com
License: MIT
Keywords: api
Platform: UNKNOWN
Classifier: Development Status :: 5 - Production/Stable
Classifier: Intended Audience :: Education
Classifier: Operating System :: Microsoft :: Windows :: Windows 10
Classifier: License :: OSI Approved :: MIT License
Classifier: Programming Language :: Python :: 3
